protobuf_inspector/__init__.py
protobuf_inspector/__main__.py
protobuf_inspector/core.py
protobuf_inspector/parser.py
protobuf_inspector/types.py
protobuf_inspector-0.2.dist-info/LICENSE
protobuf_inspector-0.2.dist-info/METADATA
protobuf_inspector-0.2.dist-info/WHEEL
protobuf_inspector-0.2.dist-info/entry_points.txt
protobuf_inspector-0.2.dist-info/top_level.txt
protobuf_inspector-0.2.dist-info/RECORD
