Metadata-Version: 2.1
Name: protobuf-inspector
Version: 0.2
Summary: Tool to reverse-engineer Protocol Buffers with unknown definition
Home-page: https://github.com/mildsunrise/protobuf-inspector
Author: Alba Mendez
Author-email: me@alba.sh
License: UNKNOWN
Platform: UNKNOWN
Classifier: Programming Language :: Python :: 3
Classifier: License :: OSI Approved :: ISC License (ISCL)
Classifier: Operating System :: OS Independent
Requires-Python: >=3.3
